hackrf/HackRF.py
hackrf/__init__.py
hackrf/config.json
hackrf/const.py
hackrf/core.py
hackrf/util.py
HackRF_SDR-1.0.0.dist-info/METADATA
HackRF_SDR-1.0.0.dist-info/WHEEL
HackRF_SDR-1.0.0.dist-info/top_level.txt
HackRF_SDR-1.0.0.dist-info/RECORD
